{
  "hippodrome": "NAPLES",
  "type_reunion": "ATTELE",
  "date_extraction": "2026-06-27T11:25:33.206269",
  "url_source": "https://online.turfinfo.api.pmu.fr/rest/client/61/programme/27062026/R8",
  "courses": [
    {
      "nom": "GRAN PREMIO FRECCIA D'EUROPA            ITALIE",
      "horaire": "22h28",
      "numero": "7",
      "type": "ATTELE",
      "distance": "1600m",
      "url": "",
      "participants": [
        {
          "n°": "1",
          "cheval": "ALRAJAH ONE M.TR. 10 a.",
          "cheval_url": "",
          "père_mère": "Par: MAHARAJAH et MARIU'",
          "corde": "(Corde:01)",
          "couleurs": "https://www.pmu.fr/back-assets/hippique/casaques/27062026/R8/C7/P1.png",
          "propriétaire": "Sc. MY HORSE S.R.L.",
          "entraineur": "A. GOCCIADORO",
          "éleveurs": "",
          "jockey": "R. VECCHIONE",
          "poids": "",
          "gains": "165019300",
          "musique": "3a1a(25)6a1a4a",
          "valeur": "",
          "equipement(s)": "",
          "nb_courses": 3,
          "nb_victoires": 0,
          "nb_places": 2,
          "cote": 7.3,
          "cote_tendance": "+",
          "cote_reference": 6.2
        },
        {
          "n°": "2",
          "cheval": "ERNESTO SPRITZ M.TR. 6 a.",
          "cheval_url": "",
          "père_mère": "Par: MAHARAJAH et REIMS KRONOS",
          "corde": "(Corde:02)",
          "couleurs": "https://www.pmu.fr/back-assets/hippique/casaques/27062026/R8/C7/P2.png",
          "propriétaire": "Scuderia VALLE FALCONERA SAS",
          "entraineur": "A. SARZETTO",
          "éleveurs": "",
          "jockey": "A. FAROLFI",
          "poids": "",
          "gains": "9334600",
          "musique": "Da5a3a2a2a",
          "valeur": "",
          "equipement(s)": "",
          "nb_courses": 0,
          "nb_victoires": 0,
          "nb_places": 0,
          "cote": 29.0,
          "cote_tendance": "+",
          "cote_reference": 25.0
        },
        {
          "n°": "3",
          "cheval": "DENVER GIO M.TR. 7 a.",
          "cheval_url": "",
          "père_mère": "Par: SOUTHWIND FRANK (US) et SWAN WISE AS",
          "corde": "(Corde:03)",
          "couleurs": "https://www.pmu.fr/back-assets/hippique/casaques/27062026/R8/C7/P3.png",
          "propriétaire": "Francesco LICCIARDI",
          "entraineur": "A. GOCCIADORO",
          "éleveurs": "",
          "jockey": "V. LUONGO",
          "poids": "",
          "gains": "7637600",
          "musique": "1a1a(25)1a1a3a",
          "valeur": "",
          "equipement(s)": "",
          "nb_courses": 1,
          "nb_victoires": 0,
          "nb_places": 0,
          "cote": 7.3,
          "cote_tendance": "+",
          "cote_reference": 6.2
        },
        {
          "n°": "4",
          "cheval": "FIL EK M.TR. 5 a.",
          "cheval_url": "",
          "père_mère": "Par: RINGOSTARR TREB et UKASE EK",
          "corde": "(Corde:04)",
          "couleurs": "https://www.pmu.fr/back-assets/hippique/casaques/27062026/R8/C7/P4.png",
          "propriétaire": "Emidio LOZZI",
          "entraineur": "F. BARELLI",
          "éleveurs": "",
          "jockey": "P. GUBELLINI",
          "poids": "",
          "gains": "19895800",
          "musique": "1a1a2aDaDa",
          "valeur": "",
          "equipement(s)": "",
          "nb_courses": 5,
          "nb_victoires": 0,
          "nb_places": 3,
          "cote": 4.2,
          "cote_tendance": "+",
          "cote_reference": 5.0
        },
        {
          "n°": "5",
          "cheval": "FUNNY GIO F.TR. 5 a.",
          "cheval_url": "",
          "père_mère": "Par: FACE TIME BOURBON et AMAZING GIO",
          "corde": "(Corde:05)",
          "couleurs": "https://www.pmu.fr/back-assets/hippique/casaques/27062026/R8/C7/P5.png",
          "propriétaire": "COMIANTALE SRL",
          "entraineur": "A. GOCCIADORO",
          "éleveurs": "",
          "jockey": "A. GOCCIADORO",
          "poids": "",
          "gains": "66684500",
          "musique": "4a3a3a(25)1a1a",
          "valeur": "",
          "equipement(s)": "",
          "nb_courses": 1,
          "nb_victoires": 0,
          "nb_places": 1,
          "cote": 6.5,
          "cote_tendance": "+",
          "cote_reference": 7.1
        },
        {
          "n°": "6",
          "cheval": "DALI PRAV F.TR. 7 a.",
          "cheval_url": "",
          "père_mère": "Par: DONATO HANOVER et LATINA PRAV",
          "corde": "(Corde:06)",
          "couleurs": "https://www.pmu.fr/back-assets/hippique/casaques/27062026/R8/C7/P6.png",
          "propriétaire": "Scuderia INDAL SRL",
          "entraineur": "A. GOCCIADORO",
          "éleveurs": "",
          "jockey": "RENE LEGATI",
          "poids": "",
          "gains": "25654600",
          "musique": "2a3a7a1a2a",
          "valeur": "",
          "equipement(s)": "",
          "nb_courses": 3,
          "nb_victoires": 0,
          "nb_places": 2,
          "cote": 14.0,
          "cote_tendance": "+",
          "cote_reference": 12.0
        },
        {
          "n°": "8",
          "cheval": "FINALMENTE PAR M.TR. 5 a.",
          "cheval_url": "",
          "père_mère": "Par: VARENNE et LUCE OK",
          "corde": "(Corde:08)",
          "couleurs": "https://www.pmu.fr/back-assets/hippique/casaques/27062026/R8/C7/P8.png",
          "propriétaire": "Scuderia FUTURA HORSES",
          "entraineur": "Giorgio X D'ALESSANDRO",
          "éleveurs": "",
          "jockey": "V.P. DELL'ANNUNZIATA",
          "poids": "",
          "gains": "9977600",
          "musique": "6a5a2a3a1a",
          "valeur": "",
          "equipement(s)": "",
          "nb_courses": 0,
          "nb_victoires": 0,
          "nb_places": 0,
          "cote": 29.0,
          "cote_tendance": "+",
          "cote_reference": 25.0
        },
        {
          "n°": "9",
          "cheval": "FOLLIA D'ESI F.TR. 5 a.",
          "cheval_url": "",
          "père_mère": "Par: RINGOSTARR TREB et TESSA D'ESI",
          "corde": "(Corde:09)",
          "couleurs": "https://www.pmu.fr/back-assets/hippique/casaques/27062026/R8/C7/P9.png",
          "propriétaire": "Francesco Graziano BIASIA",
          "entraineur": "M. BARONCINI",
          "éleveurs": "",
          "jockey": "M. STEFANI",
          "poids": "",
          "gains": "23189400",
          "musique": "1a6a3a6a1a",
          "valeur": "",
          "equipement(s)": "",
          "nb_courses": 0,
          "nb_victoires": 0,
          "nb_places": 0,
          "cote": 14.0,
          "cote_tendance": ""
        },
        {
          "n°": "10",
          "cheval": "ALWAYS EK M.TR. 10 a.",
          "cheval_url": "",
          "père_mère": "Par: FILIPP ROC et NIKE EK",
          "corde": "(Corde:10)",
          "couleurs": "https://www.pmu.fr/back-assets/hippique/casaques/27062026/R8/C7/P10.png",
          "propriétaire": "EFFEBI SRL",
          "entraineur": "A. GOCCIADORO",
          "éleveurs": "",
          "jockey": "A. DI NARDO",
          "poids": "",
          "gains": "114660300",
          "musique": "7a3a1aDa0a",
          "valeur": "",
          "equipement(s)": "",
          "nb_courses": 19,
          "nb_victoires": 6,
          "nb_places": 5,
          "cote": 9.8,
          "cote_tendance": "+",
          "cote_reference": 8.3
        }
      ]
    },
    {
      "nom": "GRAN PREMIO UNIONE EUROPEA              ITALIE",
      "horaire": "22h53",
      "numero": "8",
      "type": "ATTELE",
      "distance": "2100m",
      "url": "",
      "participants": [
        {
          "n°": "1",
          "cheval": "GIGIA DA F.TR. 4 a.",
          "cheval_url": "",
          "père_mère": "Par: GINGER UP et RHIANNA GRIF",
          "corde": "(Corde:01)",
          "couleurs": "https://www.pmu.fr/back-assets/hippique/casaques/27062026/R8/C8/P1.png",
          "propriétaire": "C. LANDOLINA",
          "entraineur": "G. LO VERDE",
          "éleveurs": "",
          "jockey": "G. LO VERDE",
          "poids": "",
          "gains": "6239500",
          "musique": "2a1a7aDa3a",
          "valeur": "",
          "equipement(s)": "",
          "nb_courses": 0,
          "nb_victoires": 0,
          "nb_places": 0
        },
        {
          "n°": "2",
          "cheval": "GIMMY TOP M.TR. 4 a.",
          "cheval_url": "",
          "père_mère": "Par: READLY EXPRESS et MELODY DEL RIO",
          "corde": "(Corde:02)",
          "couleurs": "https://www.pmu.fr/back-assets/hippique/casaques/27062026/R8/C8/P2.png",
          "propriétaire": "Luke CARUANA",
          "entraineur": "Vincenzo GALLO",
          "éleveurs": "",
          "jockey": "V. GALLO",
          "poids": "",
          "gains": "5454800",
          "musique": "6a3a2a9a3a",
          "valeur": "",
          "equipement(s)": "",
          "nb_courses": 0,
          "nb_victoires": 0,
          "nb_places": 0
        },
        {
          "n°": "3",
          "cheval": "GOLIMPIO D'OR M.TR. 4 a.",
          "cheval_url": "",
          "père_mère": "Par: DONTYOUFORGETIT (US) et ULENA GRIF",
          "corde": "(Corde:03)",
          "couleurs": "https://www.pmu.fr/back-assets/hippique/casaques/27062026/R8/C8/P3.png",
          "propriétaire": "Mario MINOPOLI",
          "entraineur": "SALVATORE MINOPOLI",
          "éleveurs": "",
          "jockey": "M. MINOPOLI JR",
          "poids": "",
          "gains": "8318000",
          "musique": "2a4aDa(25)9a6a",
          "valeur": "",
          "equipement(s)": "",
          "nb_courses": 4,
          "nb_victoires": 0,
          "nb_places": 2,
          "cote": 57.0,
          "cote_tendance": "",
          "cote_reference": 56.0
        },
        {
          "n°": "4",
          "cheval": "GINGER GIO M.TR. 4 a.",
          "cheval_url": "",
          "père_mère": "Par: TONY GIO et DORIS DEO (US)",
          "corde": "(Corde:04)",
          "couleurs": "https://www.pmu.fr/back-assets/hippique/casaques/27062026/R8/C8/P4.png",
          "propriétaire": "ZACON GIO SRL",
          "entraineur": "S. GUARATO",
          "éleveurs": "",
          "jockey": "R. VECCHIONE",
          "poids": "",
          "gains": "13220800",
          "musique": "4a0a2a9a(25)1a",
          "valeur": "",
          "equipement(s)": "",
          "nb_courses": 4,
          "nb_victoires": 1,
          "nb_places": 1,
          "cote": 57.0,
          "cote_tendance": "",
          "cote_reference": 113.0
        },
        {
          "n°": "5",
          "cheval": "GABRIOZ M.TR. 4 a.",
          "cheval_url": "",
          "père_mère": "Par: MAHARAJAH et LAETITIA (ITY)",
          "corde": "(Corde:05)",
          "couleurs": "https://www.pmu.fr/back-assets/hippique/casaques/27062026/R8/C8/P5.png",
          "propriétaire": "SCUDERIA JOLLYZ STABLE SRL",
          "entraineur": "A. GOCCIADORO",
          "éleveurs": "",
          "jockey": "A. DI NARDO",
          "poids": "",
          "gains": "39038000",
          "musique": "5a2a7a5a7a",
          "valeur": "",
          "equipement(s)": "",
          "nb_courses": 2,
          "nb_victoires": 0,
          "nb_places": 2,
          "cote": 76.0,
          "cote_tendance": "",
          "cote_reference": 75.0
        },
        {
          "n°": "6",
          "cheval": "GLAMOUR QUEEN (IT) F.TR. 4 a.",
          "cheval_url": "",
          "père_mère": "Par: FACE TIME BOURBON et PEACE OF MIND",
          "corde": "(Corde:06)",
          "couleurs": "https://www.pmu.fr/back-assets/hippique/casaques/27062026/R8/C8/P6.png",
          "propriétaire": "L. CECCHI",
          "entraineur": "A. GOCCIADORO",
          "éleveurs": "",
          "jockey": "A. SIMIOLI",
          "poids": "",
          "gains": "22342900",
          "musique": "2aDa2a1a(25)3a",
          "valeur": "",
          "equipement(s)": "",
          "nb_courses": 0,
          "nb_victoires": 0,
          "nb_places": 0,
          "cote": 28.0,
          "cote_tendance": "",
          "cote_reference": 28.0
        },
        {
          "n°": "7",
          "cheval": "GIORDAN DBL M.TR. 4 a.",
          "cheval_url": "",
          "père_mère": "Par: VICTOR GIO et ROXANA D'ETE",
          "corde": "(Corde:07)",
          "couleurs": "https://www.pmu.fr/back-assets/hippique/casaques/27062026/R8/C8/P7.png",
          "propriétaire": "T. DI STEFANO",
          "entraineur": "R. FORINO",
          "éleveurs": "",
          "jockey": "R. FORINO",
          "poids": "",
          "gains": "2014500",
          "musique": "4a5aDa(25)2a3a",
          "valeur": "",
          "equipement(s)": "",
          "nb_courses": 0,
          "nb_victoires": 0,
          "nb_places": 0
        },
        {
          "n°": "8",
          "cheval": "GALILEO FERM M.TR. 4 a.",
          "cheval_url": "",
          "père_mère": "Par: MAHARAJAH et ZIMA AXE",
          "corde": "(Corde:08)",
          "couleurs": "https://www.pmu.fr/back-assets/hippique/casaques/27062026/R8/C8/P8.png",
          "propriétaire": "Francesco Graziano BIASIA",
          "entraineur": "M. BARONCINI",
          "éleveurs": "",
          "jockey": "M. STEFANI",
          "poids": "",
          "gains": "31166600",
          "musique": "3a1a4a2a2a",
          "valeur": "",
          "equipement(s)": "",
          "nb_courses": 0,
          "nb_victoires": 0,
          "nb_places": 0
        },
        {
          "n°": "9",
          "cheval": "GUGLIELMO JET M.TR. 4 a.",
          "cheval_url": "",
          "père_mère": "Par: MAHARAJAH et NAGASAKI JET (ITY)",
          "corde": "(Corde:09)",
          "couleurs": "https://www.pmu.fr/back-assets/hippique/casaques/27062026/R8/C8/P9.png",
          "propriétaire": "Ecurie Elodie CHENET",
          "entraineur": "A. GOCCIADORO",
          "éleveurs": "",
          "jockey": "A. GOCCIADORO",
          "poids": "",
          "gains": "50911000",
          "musique": "1a1a1a2a1a",
          "valeur": "",
          "equipement(s)": "",
          "nb_courses": 5,
          "nb_victoires": 2,
          "nb_places": 3,
          "cote": 1.1,
          "cote_tendance": "",
          "cote_reference": 1.1
        }
      ]
    }
  ]
}