{
  "hippodrome": "BJERKE",
  "type_reunion": "ATTELE",
  "date_extraction": "2026-06-14T23:16:18.386262",
  "url_source": "https://online.turfinfo.api.pmu.fr/rest/client/61/programme/14062026/R5",
  "courses": [
    {
      "nom": "NETTAVISEN OSLO GRAND PRIX - UET ELITE  NORVEGE",
      "horaire": "17h45",
      "numero": "11",
      "type": "ATTELE",
      "distance": "2100m",
      "url": "",
      "participants": [
        {
          "n°": "2",
          "cheval": "BORUPS VICTORY M.TR. 8 a.",
          "cheval_url": "",
          "père_mère": "Par: GOOGOO GAAGAA et BORUPS JULIA",
          "corde": "(Corde:02)",
          "couleurs": "https://www.pmu.fr/back-assets/hippique/casaques/14062026/R5/C11/P2.png",
          "propriétaire": "Stall DROAD AB",
          "entraineur": "Daniel WAJERSTEN",
          "éleveurs": "",
          "jockey": "D. WAJERSTEN",
          "poids": "",
          "gains": "134599900",
          "musique": "5a1a1a(25)0a5a",
          "valeur": "",
          "equipement(s)": "",
          "nb_courses": 4,
          "nb_victoires": 0,
          "nb_places": 3,
          "cote": 1.8,
          "cote_tendance": "",
          "cote_reference": 3.1,
          "arrivee": 1
        },
        {
          "n°": "4",
          "cheval": "EPIC KRONOS M.TR. 6 a.",
          "cheval_url": "",
          "père_mère": "Par: MUSCLE HILL et FIREFLY",
          "corde": "(Corde:04)",
          "couleurs": "https://www.pmu.fr/back-assets/hippique/casaques/14062026/R5/C11/P4.png",
          "propriétaire": "WINGED LION BREEDING AB",
          "entraineur": "Daniel REDEN",
          "éleveurs": "",
          "jockey": "O. KIHLSTROM",
          "poids": "",
          "gains": "83466300",
          "musique": "2a4a3a(25)1a1a",
          "valeur": "",
          "equipement(s)": "",
          "nb_courses": 0,
          "nb_victoires": 0,
          "nb_places": 0,
          "cote": 3.4,
          "cote_tendance": "",
          "cote_reference": 2.5,
          "arrivee": 2
        },
        {
          "n°": "10",
          "cheval": "KUIPER M.TR. 6 a.",
          "cheval_url": "",
          "père_mère": "Par: FACE TIME BOURBON et EDDICTION",
          "corde": "(Corde:10)",
          "couleurs": "https://www.pmu.fr/back-assets/hippique/casaques/14062026/R5/C11/P10.png",
          "propriétaire": "Stall COURANT AB",
          "entraineur": "Daniel WAJERSTEN",
          "éleveurs": "",
          "jockey": "M.E. DJUSE",
          "poids": "",
          "gains": "32294100",
          "musique": "1a4a2a5aDa",
          "valeur": "",
          "equipement(s)": "",
          "nb_courses": 0,
          "nb_victoires": 0,
          "nb_places": 0,
          "cote": 17.0,
          "cote_tendance": "",
          "cote_reference": 10.0,
          "arrivee": 3
        },
        {
          "n°": "5",
          "cheval": "KENTUCKY RIVER M.TR. 8 a.",
          "cheval_url": "",
          "père_mère": "Par: FATHER PATRICK et FLICKA RIVER",
          "corde": "(Corde:05)",
          "couleurs": "https://www.pmu.fr/back-assets/hippique/casaques/14062026/R5/C11/P5.png",
          "propriétaire": "JIMMIT AB",
          "entraineur": "Daniel REDEN",
          "éleveurs": "",
          "jockey": "R.N. SKOGLUND",
          "poids": "",
          "gains": "70906200",
          "musique": "7a3a1a3a2a",
          "valeur": "",
          "equipement(s)": "",
          "nb_courses": 6,
          "nb_victoires": 0,
          "nb_places": 2,
          "cote": 30.0,
          "cote_tendance": "",
          "cote_reference": 19.0,
          "arrivee": 4
        },
        {
          "n°": "7",
          "cheval": "POWWOW M.TR. 6 a.",
          "cheval_url": "",
          "père_mère": "Par: PAPAGAYO E. et TAMAYA",
          "corde": "(Corde:07)",
          "couleurs": "https://www.pmu.fr/back-assets/hippique/casaques/14062026/R5/C11/P7.png",
          "propriétaire": "Team POWWOW",
          "entraineur": "J.K. WAALER",
          "éleveurs": "",
          "jockey": "L.A. KOLLE",
          "poids": "",
          "gains": "23707700",
          "musique": "2a0a4a(25)0a3a",
          "valeur": "",
          "equipement(s)": "",
          "nb_courses": 0,
          "nb_victoires": 0,
          "nb_places": 0,
          "cote": 118.0,
          "cote_tendance": "+",
          "cote_reference": 54.0,
          "arrivee": 5
        },
        {
          "n°": "6",
          "cheval": "GET A WISH M.TR. 8 a.",
          "cheval_url": "",
          "père_mère": "Par: WISHING STONE et AMANDA VANG",
          "corde": "(Corde:06)",
          "couleurs": "https://www.pmu.fr/back-assets/hippique/casaques/14062026/R5/C11/P6.png",
          "propriétaire": "GET A WISH STABLE",
          "entraineur": "R. BERGH",
          "éleveurs": "",
          "jockey": "R. BERGH",
          "poids": "",
          "gains": "44523900",
          "musique": "3a4a2a(25)9a3a",
          "valeur": "",
          "equipement(s)": "",
          "nb_courses": 0,
          "nb_victoires": 0,
          "nb_places": 0,
          "cote": 79.0,
          "cote_tendance": "+",
          "cote_reference": 109.0,
          "arrivee": 6
        },
        {
          "n°": "1",
          "cheval": "HARLEY GEMA F.TR. 9 a.",
          "cheval_url": "",
          "père_mère": "Par: BOLD EAGLE et REEDITE GEDE",
          "corde": "(Corde:01)",
          "couleurs": "https://www.pmu.fr/back-assets/hippique/casaques/14062026/R5/C11/P1.png",
          "propriétaire": "Ecurie Marc SASSIER",
          "entraineur": "B. GOOP",
          "éleveurs": "Mme Marie-Annick SASSIER",
          "jockey": "B. GOOP",
          "poids": "",
          "gains": "68040300",
          "musique": "0a7aDa2a1a",
          "valeur": "",
          "equipement(s)": "",
          "nb_courses": 71,
          "nb_victoires": 16,
          "nb_places": 33,
          "cote": 10.0,
          "cote_tendance": "",
          "cote_reference": 6.0,
          "arrivee": 7
        },
        {
          "n°": "3",
          "cheval": "BARON TILLY H.TR. 6 a.",
          "cheval_url": "",
          "père_mère": "Par: READY CASH et INFRA TILLY",
          "corde": "(Corde:03)",
          "couleurs": "https://www.pmu.fr/back-assets/hippique/casaques/14062026/R5/C11/P3.png",
          "propriétaire": "Stall TILLY AB",
          "entraineur": "David PERSSON",
          "éleveurs": "",
          "jockey": "C.J. JEPSON",
          "poids": "",
          "gains": "21891700",
          "musique": "2a1a(25)Da0a1a",
          "valeur": "",
          "equipement(s)": "",
          "nb_courses": 1,
          "nb_victoires": 0,
          "nb_places": 0,
          "cote": 14.0,
          "cote_tendance": "+",
          "cote_reference": 41.0
        },
        {
          "n°": "8",
          "cheval": "Y.NOT DIAMANT H.TR. 7 a.",
          "cheval_url": "",
          "père_mère": "Par: ODESSA SANTANA et NIGHTWISH DIAMANT",
          "corde": "(Corde:08)",
          "couleurs": "https://www.pmu.fr/back-assets/hippique/casaques/14062026/R5/C11/P8.png",
          "propriétaire": "Stall M.S. DIAMANTEN",
          "entraineur": "P. HAGOORT",
          "éleveurs": "",
          "jockey": "R. BAKKER",
          "poids": "",
          "gains": "31069400",
          "musique": "0a1a0a(25)0a2a",
          "valeur": "",
          "equipement(s)": "",
          "nb_courses": 0,
          "nb_victoires": 0,
          "nb_places": 0,
          "cote": 145.0,
          "cote_tendance": "+",
          "cote_reference": 131.0
        },
        {
          "n°": "9",
          "cheval": "ELDORADO JET M.TR. 6 a.",
          "cheval_url": "",
          "père_mère": "Par: TWISTER BI et RANGONA JET",
          "corde": "(Corde:09)",
          "couleurs": "https://www.pmu.fr/back-assets/hippique/casaques/14062026/R5/C11/P9.png",
          "propriétaire": "MASIOL APS",
          "entraineur": "A. GOCCIADORO",
          "éleveurs": "",
          "jockey": "M.A. DJUSE",
          "poids": "",
          "gains": "17903700",
          "musique": "2a2a2aDaDa",
          "valeur": "",
          "equipement(s)": "",
          "nb_courses": 4,
          "nb_victoires": 1,
          "nb_places": 0,
          "cote": 37.0,
          "cote_tendance": "-",
          "cote_reference": 15.0
        }
      ],
      "arrivee_definitive": true
    }
  ]
}